django_push/__init__.py
django_push/publisher/__init__.py
django_push/publisher/feeds.py
django_push/subscriber/__init__.py
django_push/subscriber/admin.py
django_push/subscriber/models.py
django_push/subscriber/signals.py
django_push/subscriber/urls.py
django_push/subscriber/utils.py
django_push/subscriber/views.py
django_push/subscriber/migrations/0001_initial.py
django_push/subscriber/migrations/__init__.py
django_push-1.1.dist-info/METADATA
django_push-1.1.dist-info/RECORD
django_push-1.1.dist-info/WHEEL
django_push-1.1.dist-info/top_level.txt
tests/__init__.py
tests/settings.py
tests/publisher/__init__.py
tests/publisher/feeds.py
tests/publisher/models.py
tests/publisher/tests.py
tests/publisher/urls.py
tests/subscribe/__init__.py
tests/subscribe/models.py
tests/subscribe/tests.py
